Html51Specification/README.md
Html51Specification/__init__.py
Html51Specification/__main__.py
Html51Specification/file.epub
Html51Specification/index.html
Html51Specification/css/__init__.py
Html51Specification/css/annotations.css
Html51Specification/css/main.css
Html51Specification/css/normalize.css
Html51Specification/css/popup.css
Html51Specification/font/__init__.py
Html51Specification/font/fontello.eot
Html51Specification/font/fontello.svg
Html51Specification/font/fontello.ttf
Html51Specification/font/fontello.woff
Html51Specification/img/__init__.py
Html51Specification/img/annotator-glyph-sprite.png
Html51Specification/img/annotator-icon-sprite.png
Html51Specification/img/apple-touch-icon.png
Html51Specification/img/cancelfullscreen.png
Html51Specification/img/close.png
Html51Specification/img/fullscreen.png
Html51Specification/img/loader.gif
Html51Specification/img/menu-icon.png
Html51Specification/img/save.png
Html51Specification/img/saved.png
Html51Specification/img/settings-s.png
Html51Specification/img/settings.png
Html51Specification/img/star.png
Html51Specification/js/__init__.py
Html51Specification/js/epub.js
Html51Specification/js/epub.min.js
Html51Specification/js/epub.min.map
Html51Specification/js/hooks.min.js
Html51Specification/js/hooks.min.map
Html51Specification/js/reader.js
Html51Specification/js/reader.js.map
Html51Specification/js/reader.min.js
Html51Specification/js/reader.min.map
Html51Specification/js/hooks/__init__.py
Html51Specification/js/hooks/extensions/__init__.py
Html51Specification/js/hooks/extensions/highlight.js
Html51Specification/js/libs/__init__.py
Html51Specification/js/libs/jquery.min.js
Html51Specification/js/libs/localforage.min.js
Html51Specification/js/libs/screenfull.js
Html51Specification/js/libs/screenfull.min.js
Html51Specification/js/libs/zip.min.js
Html51Specification/js/plugins/__init__.py
Html51Specification/js/plugins/hypothesis.js
Html51Specification/js/plugins/search.js
html_5_1_specification-2024.3.1.0.dist-info/METADATA
html_5_1_specification-2024.3.1.0.dist-info/WHEEL
html_5_1_specification-2024.3.1.0.dist-info/entry_points.txt
html_5_1_specification-2024.3.1.0.dist-info/top_level.txt
html_5_1_specification-2024.3.1.0.dist-info/RECORD
